ch0/__init__.py
ch0/__main__.py
ch0/cli.py
ch0/engines/__init__.py
ch0/engines/sunfish.py
ch0/engines/uci.py
ch0/engines/andoma/LICENSE
ch0/engines/andoma/README.md
ch0/engines/andoma/__init__.py
ch0/engines/andoma/communication.py
ch0/engines/andoma/evaluate.py
ch0/engines/andoma/main.py
ch0/engines/andoma/movegeneration.py
ch0/engines/andoma/requirements-dev.txt
ch0/engines/andoma/requirements.txt
ch0/engines/andoma/uci-interface.md
ch0/engines/andoma/ui.py
ch0/engines/sunfish/LICENSE.md
ch0/engines/sunfish/README.md
ch0/engines/sunfish/__init__.py
ch0/engines/sunfish/main.py
ch0/engines/sunfish/packed.sh
ch0/engines/sunfish/sunfish.py
ch0/engines/sunfish/sunfish_uci.py
ch0/engines/sunfish/tools/fancy.py
ch0/engines/sunfish/tools/quick_tests.sh
ch0/engines/sunfish/tools/test.sh
ch0/engines/sunfish/tools/tester.py
ch0/engines/sunfish/tools/uci.py
play_ch0-1.3.4.dist-info/METADATA
play_ch0-1.3.4.dist-info/WHEEL
play_ch0-1.3.4.dist-info/entry_points.txt
play_ch0-1.3.4.dist-info/licenses/LICENSE
play_ch0-1.3.4.dist-info/RECORD
