Metadata-Version: 2.4
Name: play-ch0
Version: 1.3.4
Summary: Blindfold chess CLI with built-in engines
Project-URL: Homepage, https://github.com/menisadi/ch0
Project-URL: Repository, https://github.com/menisadi/ch0
Project-URL: Changelog, https://github.com/menisadi/ch0/blob/main/CHANGELOG.md
Project-URL: Releases, https://github.com/menisadi/ch0/releases
Author: menisadi
License: GNU GENERAL PUBLIC LICENSE
License-File: LICENSE
Classifier: License :: OSI Approved :: GNU General Public License v3 (GPLv3)
Classifier: Programming Language :: Python :: 3
Requires-Python: >=3.11
Requires-Dist: chess>=1.11.2
